astromorph/__init__.py
astromorph/__main__.py
astromorph/app.py
astromorph/pipeline_01_training.py
astromorph/pipeline_02_inference.py
astromorph/settings.py
astromorph/byol/__init__.py
astromorph/byol/byol.py
astromorph/byol/byol_trainer.py
astromorph/byol/min_max_norm.py
astromorph/byol/mlp.py
astromorph/byol/netwrapper.py
astromorph/datasets/__init__.py
astromorph/datasets/base_dataset.py
astromorph/datasets/filelist_dataset.py
astromorph/datasets/helpers.py
astromorph/models/__init__.py
astromorph/models/astro_morphology_model.py
astromorph/models/fewer_layers_resnet.py
astromorph-0.1.2.dist-info/licenses/LICENSE
tests/conftest.py
tests/test_training.py
astromorph-0.1.2.dist-info/METADATA
astromorph-0.1.2.dist-info/WHEEL
astromorph-0.1.2.dist-info/entry_points.txt
astromorph-0.1.2.dist-info/top_level.txt
astromorph-0.1.2.dist-info/RECORD
