Metadata-Version: 2.4
Name: astromorph
Version: 0.1.2
Summary: Astromorph tool
Requires-Python: <3.13.0,>=3.12.0
License-File: LICENSE
Requires-Dist: astropy>=6.0.1
Requires-Dist: loguru>=0.7.2
Requires-Dist: numpy>=1.26.4
Requires-Dist: pandas>=2.2.2
Requires-Dist: pydantic>=2.7.1
Requires-Dist: scikit-image>=0.0
Requires-Dist: scikit-learn>=1.4.2
Requires-Dist: scipy>=1.13.0
Requires-Dist: tensorboard>=2.16.2
Requires-Dist: torch>=2.3.0
Requires-Dist: torchvision>=0.18.0
Requires-Dist: tqdm>=4.66.2
Requires-Dist: typer>=0.15.2
Dynamic: license-file
